ory_kratos_client/__init__.py
ory_kratos_client/api_client.py
ory_kratos_client/api_response.py
ory_kratos_client/configuration.py
ory_kratos_client/exceptions.py
ory_kratos_client/py.typed
ory_kratos_client/rest.py
ory_kratos_client/api/__init__.py
ory_kratos_client/api/courier_api.py
ory_kratos_client/api/frontend_api.py
ory_kratos_client/api/identity_api.py
ory_kratos_client/api/metadata_api.py
ory_kratos_client/models/__init__.py
ory_kratos_client/models/authenticator_assurance_level.py
ory_kratos_client/models/batch_patch_identities_response.py
ory_kratos_client/models/consistency_request_parameters.py
ory_kratos_client/models/continue_with.py
ory_kratos_client/models/continue_with_recovery_ui.py
ory_kratos_client/models/continue_with_recovery_ui_flow.py
ory_kratos_client/models/continue_with_redirect_browser_to.py
ory_kratos_client/models/continue_with_set_ory_session_token.py
ory_kratos_client/models/continue_with_settings_ui.py
ory_kratos_client/models/continue_with_settings_ui_flow.py
ory_kratos_client/models/continue_with_verification_ui.py
ory_kratos_client/models/continue_with_verification_ui_flow.py
ory_kratos_client/models/courier_message_status.py
ory_kratos_client/models/courier_message_type.py
ory_kratos_client/models/create_fedcm_flow_response.py
ory_kratos_client/models/create_identity_body.py
ory_kratos_client/models/create_recovery_code_for_identity_body.py
ory_kratos_client/models/create_recovery_link_for_identity_body.py
ory_kratos_client/models/delete_my_sessions_count.py
ory_kratos_client/models/error_authenticator_assurance_level_not_satisfied.py
ory_kratos_client/models/error_browser_location_change_required.py
ory_kratos_client/models/error_flow_replaced.py
ory_kratos_client/models/error_generic.py
ory_kratos_client/models/flow_error.py
ory_kratos_client/models/generic_error.py
ory_kratos_client/models/get_version200_response.py
ory_kratos_client/models/health_not_ready_status.py
ory_kratos_client/models/health_status.py
ory_kratos_client-25.4.0.dist-info/LICENSE
ory_kratos_client-25.4.0.dist-info/METADATA
ory_kratos_client-25.4.0.dist-info/WHEEL
ory_kratos_client-25.4.0.dist-info/top_level.txt
ory_kratos_client-25.4.0.dist-info/RECORD
